README.md
setup.cfg
setup.py
geckordp/__init__.py
geckordp/buffers.py
geckordp/firefox.py
geckordp/logger.py
geckordp/profile.py
geckordp/rdp_client.py
geckordp/settings.py
geckordp/utils.py
geckordp.egg-info/PKG-INFO
geckordp.egg-info/SOURCES.txt
geckordp.egg-info/dependency_links.txt
geckordp.egg-info/requires.txt
geckordp.egg-info/top_level.txt
geckordp/actors/__init__.py
geckordp/actors/actor.py
geckordp/actors/device.py
geckordp/actors/events.py
geckordp/actors/heap_snapshot.py
geckordp/actors/inspector.py
geckordp/actors/memory.py
geckordp/actors/network_content.py
geckordp/actors/network_event.py
geckordp/actors/network_parent.py
geckordp/actors/node.py
geckordp/actors/node_list.py
geckordp/actors/preference.py
geckordp/actors/resources.py
geckordp/actors/root.py
geckordp/actors/screenshot.py
geckordp/actors/source.py
geckordp/actors/storage.py
geckordp/actors/string.py
geckordp/actors/target_configuration.py
geckordp/actors/thread.py
geckordp/actors/thread_configuration.py
geckordp/actors/walker.py
geckordp/actors/watcher.py
geckordp/actors/web_console.py
geckordp/actors/accessibility/__init__.py
geckordp/actors/accessibility/accessibility.py
geckordp/actors/accessibility/accessible.py
geckordp/actors/accessibility/accessible_walker.py
geckordp/actors/accessibility/parent_accessibility.py
geckordp/actors/accessibility/simulator.py
geckordp/actors/addon/__init__.py
geckordp/actors/addon/addons.py
geckordp/actors/addon/web_extension_inspected_window.py
geckordp/actors/descriptors/__init__.py
geckordp/actors/descriptors/process.py
geckordp/actors/descriptors/tab.py
geckordp/actors/descriptors/web_extension.py
geckordp/actors/descriptors/worker.py
geckordp/actors/targets/__init__.py
geckordp/actors/targets/content_process.py
geckordp/actors/targets/window_global.py
tests/actors/__init__.py
tests/actors/test_device.py
tests/actors/test_heap_snapshot.py
tests/actors/test_inspector.py
tests/actors/test_memory.py
tests/actors/test_network_content.py
tests/actors/test_network_event.py
tests/actors/test_network_parent.py
tests/actors/test_node.py
tests/actors/test_node_list.py
tests/actors/test_preference.py
