Metadata-Version: 2.1
Name: geckordp
Version: 0.5.0
Summary: A client implementation of Firefox DevTools over remote debug protocol
Home-page: https://github.com/jpramosi/geckordp
Author: jpramosi
Author-email: jimmy.pramosi@protonmail.com
License: MIT
Project-URL: Documentation, https://jpramosi.github.io/geckordp
Project-URL: Source, https://github.com/jpramosi/geckordp
Keywords: rdp remote-debug-protocol firefox crawler debug webconsole ui-testing
Platform: UNKNOWN
Classifier: License :: OSI Approved :: MIT License
Classifier: Natural Language :: English
Classifier: Operating System :: OS Independent
Classifier: Development Status :: 4 - Beta
Classifier: Intended Audience :: Developers
Classifier: Programming Language :: Python
Classifier: Programming Language :: Python :: 3.10
Provides-Extra: develop
